synckeys/__init__.py
synckeys/synckeys.py
synckeys-1.0.1.dist-info/DESCRIPTION.rst
synckeys-1.0.1.dist-info/entry_points.txt
synckeys-1.0.1.dist-info/METADATA
synckeys-1.0.1.dist-info/metadata.json
synckeys-1.0.1.dist-info/RECORD
synckeys-1.0.1.dist-info/top_level.txt
synckeys-1.0.1.dist-info/WHEEL
