Metadata-Version: 2.0
Name: synckeys
Version: 1.0.1
Summary: A simple script to manage the deployment of your ssh keys on your servers
Home-page: https://github.com/theodo/synckeys
Author: Theodo
Author-email: dev@theodo.fr
License: MIT
Keywords: ssh keys infrastructure servers
Platform: UNKNOWN
Classifier: Development Status :: 5 - Production/Stable
Classifier: Intended Audience :: System Administrators
Classifier: Topic :: System :: Systems Administration :: Authentication/Directory
Classifier: License :: OSI Approved :: MIT License
Classifier: Programming Language :: Python :: 2
Classifier: Programming Language :: Python :: 2.6
Classifier: Programming Language :: Python :: 2.7
Classifier: Programming Language :: Python :: 3
Classifier: Programming Language :: Python :: 3.2
Classifier: Programming Language :: Python :: 3.3
Classifier: Programming Language :: Python :: 3.4
Requires-Dist: ansible (>=1.9)
Provides-Extra: test
Provides-Extra: dev
